CHANGES.txt
LICENSE.txt
MANIFEST.in
README.txt
setup.py
src/p01/__init__.py
src/p01.fswidget.egg-info/PKG-INFO
src/p01.fswidget.egg-info/SOURCES.txt
src/p01.fswidget.egg-info/dependency_links.txt
src/p01.fswidget.egg-info/namespace_packages.txt
src/p01.fswidget.egg-info/not-zip-safe
src/p01.fswidget.egg-info/requires.txt
src/p01.fswidget.egg-info/top_level.txt
src/p01/fswidget/__init__.py
src/p01/fswidget/cleanupfilename.txt
src/p01/fswidget/configure.zcml
src/p01/fswidget/converter.py
src/p01/fswidget/error.py
src/p01/fswidget/interfaces.py
src/p01/fswidget/layer.py
src/p01/fswidget/tests.py
src/p01/fswidget/widget.py
src/p01/fswidget/widget_display.pt
src/p01/fswidget/widget_input.pt